topsis/__init__.py
topsis/main.py
Topsis_Puranjay_102003384-0.3.0.dist-info/License.txt
Topsis_Puranjay_102003384-0.3.0.dist-info/METADATA
Topsis_Puranjay_102003384-0.3.0.dist-info/WHEEL
Topsis_Puranjay_102003384-0.3.0.dist-info/entry_points.txt
Topsis_Puranjay_102003384-0.3.0.dist-info/top_level.txt
Topsis_Puranjay_102003384-0.3.0.dist-info/RECORD
